discophon/__init__.py
discophon/benchmark.py
discophon/py.typed
discophon/core/__init__.py
discophon/core/data.py
discophon/core/languages.py
discophon/core/validation.py
discophon/core/assets/phonology.json
discophon/core/assets/sonority.json
discophon/core/assets/tipa.json
discophon/evaluate/__init__.py
discophon/evaluate/__main__.py
discophon/evaluate/abx.py
discophon/evaluate/boundaries.py
discophon/evaluate/evaluate.py
discophon/evaluate/per.py
discophon/evaluate/pnmi.py
discophon/prepare/__init__.py
discophon/prepare/__main__.py
discophon/prepare/core.py
discophon-0.0.3.dist-info/METADATA
discophon-0.0.3.dist-info/WHEEL
discophon-0.0.3.dist-info/licenses/LICENSE
discophon-0.0.3.dist-info/RECORD
