Metadata-Version: 2.4
Name: discophon
Version: 0.0.3
Summary: The Phoneme Discovery Benchmark
Author-email: CoML <dev@cognitive-ml.fr>
License-Expression: MIT
License-File: LICENSE
Requires-Python: >=3.12
Requires-Dist: filelock>=3.20.2
Requires-Dist: httpx>=0.28.1
Requires-Dist: joblib>=1.5.3
Requires-Dist: numba>=0.63.1
Requires-Dist: numpy>=2.3.5
Requires-Dist: polars>=1.36.1
Requires-Dist: praat-textgrids>=1.4.0
Requires-Dist: soundfile>=0.13.1
Requires-Dist: soxr>=1.0.0
Requires-Dist: tqdm>=4.67.1
Requires-Dist: xarray>=2025.12.0
Provides-Extra: abx
Requires-Dist: fastabx>=0.6.1; extra == 'abx'
